cacca-1.0.0.dist-info/METADATA
cacca-1.0.0.dist-info/WHEEL
cacca-1.0.0.dist-info/entry_points.txt
cacca-1.0.0.dist-info/licenses/LICENSE
cacca/__init__.py
cacca/cli.py
cacca/constants.py
cacca/helpers.py
cacca/lib.py
cacca/node.py
cacca/playground.py
cacca/stubs.py
cacca/types/__init__.py
cacca/types/generics.py
cacca/types/layers.py
cacca-1.0.0.dist-info/RECORD
