Metadata-Version: 2.1
Name: cacca
Version: 1.0.0
Summary: A workflow framework, easy as shit.
Author-Email: Airscript <francesco@airscript.it>
License: MIT
Requires-Python: <3.13,>=3.11
